__init__.py
config.py
constants.py
graph_state.py
workflow_builder.py
agents/base_custom_agent.py
agents/base_react_agent.py
agents/auditor/agent.py
agents/auditor/agent_types.py
agents/auditor/prompts.py
agents/base_step_executing_agent/__init__.py
agents/base_step_executing_agent/agent_types.py
agents/base_step_executing_agent/base_step_executing_agent.py
agents/base_step_executing_agent/constants.py
agents/base_step_executing_agent/prompts.py
agents/installer/agent.py
agents/installer/prompts.py
agents/planner/agent.py
agents/planner/agent_types.py
agents/planner/prompts.py
agents/runner/agent.py
agents/runner/prompts.py
agents/success_verifier/agent.py
agents/success_verifier/agent_types.py
agents/success_verifier/constants.py
agents/success_verifier/prompts.py
cli/app.py
cli/scripts/setup.py
detect_secrets/__init__.py
detect_secrets/settings.py
detect_secrets/core/__init__.py
detect_secrets/core/potential_secret.py
detect_secrets/core/scan.py
detect_secrets/core/secrets_collection.py
detect_secrets/filters/base_secret_filter.py
detect_secrets/filters/filters/__init__.py
detect_secrets/filters/filters/non_alphanumeric_filter.py
detect_secrets/filters/filters/sequential_string_filter.py
detect_secrets/filters/filters/templated_secret_filter.py
detect_secrets/filters/filters/uuid_filter.py
detect_secrets/filters/filters/gibberish/__init__.py
detect_secrets/filters/filters/gibberish/gibberish_filter.py
detect_secrets/filters/filters/gibberish/rfc.model
detect_secrets/plugins/__init__.py
detect_secrets/plugins/artifactory.py
detect_secrets/plugins/aws.py
detect_secrets/plugins/azure_storage_key.py
detect_secrets/plugins/base.py
detect_secrets/plugins/basic_auth.py
detect_secrets/plugins/cloudant.py
detect_secrets/plugins/discord.py
detect_secrets/plugins/github_token.py
detect_secrets/plugins/gitlab_token.py
detect_secrets/plugins/high_entropy_strings.py
detect_secrets/plugins/ibm_cloud_iam.py
detect_secrets/plugins/ibm_cos_hmac.py
setup_agent-0.2.6.dist-info/METADATA
setup_agent-0.2.6.dist-info/WHEEL
setup_agent-0.2.6.dist-info/entry_points.txt
setup_agent-0.2.6.dist-info/top_level.txt
setup_agent-0.2.6.dist-info/RECORD
