Metadata-Version: 2.4
Name: setup-agent
Version: 0.2.6
Summary: AI agent for installing tools and running projects.
Requires-Python: >=3.13
Requires-Dist: dotenv>=0.9.9
Requires-Dist: gibberish-detector>=0.1.1
Requires-Dist: langchain==1.0.4
Requires-Dist: langchain-anthropic>=0.3.22
Requires-Dist: langchain-community>=0.3.31
Requires-Dist: langchain-core>=0.3.75
Requires-Dist: langchain-openai>=0.3.32
Requires-Dist: langchain-tavily>=0.2.11
Requires-Dist: langchain-text-splitters>=1.0.0
Requires-Dist: langgraph==1.0.2
Requires-Dist: langsmith==0.4.39
Requires-Dist: markdown>=3.9
Requires-Dist: pandoc>=2.4
Requires-Dist: pexpect>=4.9.0
Requires-Dist: pre-commit>=4.3.0
Requires-Dist: pyahocorasick>=2.2.0
Requires-Dist: questionary>=2.1.1
Requires-Dist: rich>=14.2.0
Requires-Dist: typer>=0.20.0
Requires-Dist: unidiff>=0.7.5
Requires-Dist: unstructured>=0.18.15
